setup.py
pypi_t1t2t10/__init__.py
pypi_t1t2t10/test01.py
pypi_t1t2t10/test02.py
pypi_t1t2t10.egg-info/PKG-INFO
pypi_t1t2t10.egg-info/SOURCES.txt
pypi_t1t2t10.egg-info/dependency_links.txt
pypi_t1t2t10.egg-info/top_level.txt
pypi_t1t2t10.egg-info/zip-safe