Metadata-Version: 1.1
Name: pypi-t1t2t10
Version: 1.0.1
Summary: this is a test package for packing python liberaries tutorial.
Home-page: https://github.com/WangYan969/turing.git
Author: WangYan
Author-email: youremail@email.com
License: MIT
Keywords: test python package
Platform: UNKNOWN
Classifier: License :: OSI Approved :: MIT License
Classifier: Programming Language :: Python
Classifier: Intended Audience :: Developers
Classifier: Operating System :: OS Independent
